xaiensembleapi/__init__.py
xaiensembleapi/xaiensemble.py
XaI_Ensemble_API-0.2.0.dist-info/METADATA
XaI_Ensemble_API-0.2.0.dist-info/WHEEL
XaI_Ensemble_API-0.2.0.dist-info/top_level.txt
XaI_Ensemble_API-0.2.0.dist-info/RECORD
