Metadata-Version: 2.1
Name: XaI-Ensemble-API
Version: 0.2.0
Summary: A library for do the explaination of data using a new ensenble of XAI methods
Author: Michael Lopes Bastos
Author-email: mlb@cin.ufpe.br
Classifier: Programming Language :: Python :: 3
Classifier: License :: OSI Approved :: MIT License
Classifier: Operating System :: OS Independent
Requires-Python: >=3.6
Requires-Dist: lime==0.1.1.37
Requires-Dist: shap==0.46.0
Requires-Dist: wheel
